yyam/__init__.py
yyam/__main__.py
yyam/add.py
yyam/config.py
yyam/console_io.py
yyam/delete.py
yyam/list_item.py
yyam/modify.py
yyam/search.py
yyam/tomdb.py
yyam/tomrw.py
yyam-0.1.4.dist-info/LICENSE
yyam-0.1.4.dist-info/METADATA
yyam-0.1.4.dist-info/WHEEL
yyam-0.1.4.dist-info/entry_points.txt
yyam-0.1.4.dist-info/top_level.txt
yyam-0.1.4.dist-info/RECORD
